generic_notifications/__init__.py
generic_notifications/apps.py
generic_notifications/channels.py
generic_notifications/digest.py
generic_notifications/frequencies.py
generic_notifications/management/__init__.py
generic_notifications/management/commands/__init__.py
generic_notifications/management/commands/send_notification_digests.py
generic_notifications/migrations/0001_initial.py
generic_notifications/migrations/0002_alter_disablednotificationtypechannel_id_and_more.py
generic_notifications/migrations/0003_remove_notification_notification_channels_gin_and_more.py
generic_notifications/migrations/0004_rename_emailfrequency_notificationfrequency.py
generic_notifications/migrations/0005_alter_notificationfrequency_options_and_more.py
generic_notifications/migrations/0006_alter_notificationfrequency_unique_together_and_more.py
generic_notifications/migrations/__init__.py
generic_notifications/models.py
generic_notifications/preferences.py
generic_notifications/registry.py
generic_notifications/types.py
generic_notifications/utils.py
django_generic_notifications-2.3.3.dist-info/licenses/LICENSE
django_generic_notifications-2.3.3.dist-info/WHEEL
django_generic_notifications-2.3.3.dist-info/METADATA
django_generic_notifications-2.3.3.dist-info/RECORD
