Metadata-Version: 2.4
Name: django-generic-notifications
Version: 2.3.3
Summary: A flexible, multi-channel notification system for Django applications with built-in support for email digests, user preferences, and extensible delivery channels.
Keywords: django,notifications,email,digest,multi-channel
Author: Kevin Renskers
Author-email: Kevin Renskers <kevin@loopwerk.io>
License-Expression: MIT
License-File: LICENSE
Classifier: License :: OSI Approved :: MIT License
Classifier: Development Status :: 5 - Production/Stable
Classifier: Intended Audience :: Developers
Classifier: Framework :: Django
Classifier: Framework :: Django :: 4.2
Classifier: Framework :: Django :: 5.0
Classifier: Framework :: Django :: 5.1
Classifier: Framework :: Django :: 5.2
Classifier: Framework :: Django :: 6.0
Classifier: Programming Language :: Python
Classifier: Programming Language :: Python :: 3.10
Classifier: Programming Language :: Python :: 3.11
Classifier: Programming Language :: Python :: 3.12
Classifier: Programming Language :: Python :: 3.13
Classifier: Programming Language :: Python :: 3.14
Classifier: Programming Language :: Python :: 3.15
Requires-Dist: django>=4.2.0
Requires-Python: >=3.10
Project-URL: Homepage, https://github.com/loopwerk/django-generic-notifications/
Project-URL: Issues, https://github.com/loopwerk/django-generic-notifications/issues
Project-URL: Repository, https://github.com/loopwerk/django-generic-notifications.git
